{
    "backend": "flask",
    "db_name": "",
    "db_pass": "",
    "db_type": "mysql",
    "db_user": "",
    "dbms": "1",
    "description": "generated product",
    "design": "datta-able",
    "docker": "0",
    "err_code": 0,
    "frontend": "",
    "heroku": "0",
    "pattern": "mvc",
    "pro": "0",
    "task_id": "2a21a6d3-8234-44d7-9796-0a9dda79800c",
    "task_info": "Upload Sources [0%] - 144 files",
    "task_output": "2a21a6d3-8234-44d7-9796-0a9dda79800c.zip",
    "task_result": "SUCCESS",
    "task_state": "RUNNING",
    "task_ts_end": "2024-11-04-16-36-55",
    "task_ts_start": "2024-11-04-16-36-53"
}